oneutil/__init__.py
oneutil/logging.py
oneutil/etl/__init__.py
oneutil/etl/aws.py
oneutil/etl/databento.py
oneutil-0.0.4.dist-info/LICENSE
oneutil-0.0.4.dist-info/METADATA
oneutil-0.0.4.dist-info/WHEEL
oneutil-0.0.4.dist-info/top_level.txt
oneutil-0.0.4.dist-info/RECORD
