Metadata-Version: 2.1
Name: oneutil
Version: 0.0.4
Summary: OneSquared Utilities
Author: Shawn Lin
Requires-Python: >=3.6
License-File: LICENSE
Requires-Dist: boto3 (>=1.18.0)
